sparrowhawk/__init__.py
sparrowhawk-0.0.1.dist-info/LICENSE
sparrowhawk-0.0.1.dist-info/METADATA
sparrowhawk-0.0.1.dist-info/WHEEL
sparrowhawk-0.0.1.dist-info/top_level.txt
sparrowhawk-0.0.1.dist-info/RECORD
