Metadata-Version: 2.1
Name: sparrowhawk
Version: 0.0.1
Summary: A bot builder for discord.py
Home-page: https://github.com/vcokltfre/sparrowhawk
Author: vcokltfre
Author-email: vcokltfre@gmail.com
License: UNKNOWN
Platform: UNKNOWN
Classifier: Programming Language :: Python :: 3
Classifier: License :: OSI Approved :: MIT License
Classifier: Operating System :: OS Independent
Requires-Python: >=3.6
